MANIFEST.in
README.rst
setup.cfg
setup.py
django_tables2/__init__.py
django_tables2/config.py
django_tables2/models.py
django_tables2/rows.py
django_tables2/tables.py
django_tables2/utils.py
django_tables2/views.py
django_tables2/columns/__init__.py
django_tables2/columns/base.py
django_tables2/columns/booleancolumn.py
django_tables2/columns/checkboxcolumn.py
django_tables2/columns/datecolumn.py
django_tables2/columns/datetimecolumn.py
django_tables2/columns/emailcolumn.py
django_tables2/columns/filecolumn.py
django_tables2/columns/linkcolumn.py
django_tables2/columns/templatecolumn.py
django_tables2/columns/timecolumn.py
django_tables2/columns/urlcolumn.py
django_tables2/locale/el/LC_MESSAGES/django.mo
django_tables2/locale/el/LC_MESSAGES/django.po
django_tables2/locale/en/LC_MESSAGES/django.mo
django_tables2/locale/en/LC_MESSAGES/django.po
django_tables2/locale/es/LC_MESSAGES/django.mo
django_tables2/locale/es/LC_MESSAGES/django.po
django_tables2/locale/fr/LC_MESSAGES/django.mo
django_tables2/locale/fr/LC_MESSAGES/django.po
django_tables2/locale/pl/LC_MESSAGES/django.mo
django_tables2/locale/pl/LC_MESSAGES/django.po
django_tables2/locale/pt_PT/LC_MESSAGES/django.mo
django_tables2/locale/pt_PT/LC_MESSAGES/django.po
django_tables2/static/django_tables2/themes/paleblue/css/screen.css
django_tables2/static/django_tables2/themes/paleblue/img/arrow-active-down.png
django_tables2/static/django_tables2/themes/paleblue/img/arrow-active-up.png
django_tables2/static/django_tables2/themes/paleblue/img/arrow-inactive-down.png
django_tables2/static/django_tables2/themes/paleblue/img/arrow-inactive-up.png
django_tables2/static/django_tables2/themes/paleblue/img/false.gif
django_tables2/static/django_tables2/themes/paleblue/img/header-bg.png
django_tables2/static/django_tables2/themes/paleblue/img/missing.png
django_tables2/static/django_tables2/themes/paleblue/img/pagination-bg.gif
django_tables2/static/django_tables2/themes/paleblue/img/true.gif
django_tables3.egg-info/PKG-INFO
django_tables3.egg-info/SOURCES.txt
django_tables3.egg-info/dependency_links.txt
django_tables3.egg-info/requires.txt
django_tables3.egg-info/top_level.txt
