Metadata-Version: 1.1
Name: django-tables3
Version: 0.14.1
Summary: Table/data-grid framework for Django
Home-page: https://github.com/bradleyayers/django-tables2/
Author: Ionel Cristian Mărieș
Author-email: contact@ionelmc.ro
License: Simplified BSD
Platform: UNKNOWN
Classifier: Environment :: Web Environment
Classifier: Framework :: Django
Classifier: Intended Audience :: Developers
Classifier: License :: OSI Approved :: BSD License
Classifier: Operating System :: OS Independent
Classifier: Programming Language :: Python
Classifier: Topic :: Internet :: WWW/HTTP
Classifier: Topic :: Software Development :: Libraries
